probdistributions_gb/Binomialdistribution.py
probdistributions_gb/Gaussiandistribution.py
probdistributions_gb/Generaldistribution.py
probdistributions_gb/__init__.py
probdistributions_gb-1.1.dist-info/METADATA
probdistributions_gb-1.1.dist-info/WHEEL
probdistributions_gb-1.1.dist-info/top_level.txt
probdistributions_gb-1.1.dist-info/RECORD
