Metadata-Version: 2.1
Name: probdistributions-gb
Version: 1.1
Summary: Gaussian and Binomial Distributions
Author: Maitri Banga
